{
  "strategy": "kicktipp_exploit_engine",
  "draw_floor": 0.3,
  "draw_favorite_ceiling": 0.65,
  "tuned_at": "2026-07-14T06:30:48.988781Z",
  "training_matches": 24,
  "training_points": 47,
  "training_average_points": 1.958,
  "top_grid": [
    {
      "points": 47,
      "draw_floor": 0.3,
      "draw_favorite_ceiling": 0.65
    },
    {
      "points": 47,
      "draw_floor": 0.3,
      "draw_favorite_ceiling": 0.64
    },
    {
      "points": 47,
      "draw_floor": 0.3,
      "draw_favorite_ceiling": 0.66
    },
    {
      "points": 47,
      "draw_floor": 0.3,
      "draw_favorite_ceiling": 0.63
    },
    {
      "points": 47,
      "draw_floor": 0.3,
      "draw_favorite_ceiling": 0.67
    },
    {
      "points": 47,
      "draw_floor": 0.3,
      "draw_favorite_ceiling": 0.62
    },
    {
      "points": 47,
      "draw_floor": 0.3,
      "draw_favorite_ceiling": 0.68
    },
    {
      "points": 47,
      "draw_floor": 0.3,
      "draw_favorite_ceiling": 0.69
    },
    {
      "points": 47,
      "draw_floor": 0.3,
      "draw_favorite_ceiling": 0.61
    },
    {
      "points": 47,
      "draw_floor": 0.3,
      "draw_favorite_ceiling": 0.7
    }
  ],
  "guardrails": {
    "note": "Thresholds are backtest-tuned on current tournament results. This is for KickTipp scoring, not betting.",
    "min_training_matches_for_trust": 12
  }
}
